strategy/__init__.py
strategy/__main__.py
strategy/helpers.py
strategy/strategy.py
strat-0.0.1.dev0.dist-info/LICENSE
strat-0.0.1.dev0.dist-info/METADATA
strat-0.0.1.dev0.dist-info/WHEEL
strat-0.0.1.dev0.dist-info/top_level.txt
strat-0.0.1.dev0.dist-info/RECORD
